coreset_sc-0.1.5.dist-info/METADATA
coreset_sc-0.1.5.dist-info/WHEEL
coreset_sc-0.1.5.dist-info/licenses/LICENSE
coreset_sc/__init__.py
coreset_sc/coreset_sc.cp311-win32.pyd
coreset_sc/csc.py
coreset_sc/utils.py
coreset_sc-0.1.5.dist-info/RECORD
