Metadata-Version: 2.4
Name: coreset-sc
Version: 0.1.5
Classifier: Programming Language :: Rust
Classifier: Programming Language :: Python :: Implementation :: CPython
Classifier: Programming Language :: Python :: Implementation :: PyPy
Requires-Dist: numpy>=1.20
Requires-Dist: pre-commit>=3.5.0
Requires-Dist: pytest>=8.3.5
Requires-Dist: scikit-learn>=1.0
Requires-Dist: scipy>=1.0
License-File: LICENSE
Requires-Python: >=3.8
